banyan/__init__.py
banyan/main.py
banyan/api/__init__.py
banyan/api/access_tier.py
banyan/api/api_key.py
banyan/api/attachment.py
banyan/api/audit.py
banyan/api/base.py
banyan/api/cloud_resource.py
banyan/api/connector.py
banyan/api/device.py
banyan/api/discovered_resource.py
banyan/api/event_v2.py
banyan/api/netagent.py
banyan/api/policy.py
banyan/api/role.py
banyan/api/service.py
banyan/api/service_infra.py
banyan/api/service_tunnel.py
banyan/api/service_web.py
banyan/api/shield.py
banyan/api/user.py
banyan/controllers/__init__.py
banyan/controllers/access_tier.py
banyan/controllers/admin.py
banyan/controllers/api_key.py
banyan/controllers/audit.py
banyan/controllers/base.py
banyan/controllers/cloud_resource.py
banyan/controllers/connector.py
banyan/controllers/device.py
banyan/controllers/discovered_resource.py
banyan/controllers/event.py
banyan/controllers/export.py
banyan/controllers/netagent.py
banyan/controllers/policy.py
banyan/controllers/role.py
banyan/controllers/service.py
banyan/controllers/service_infra.py
banyan/controllers/service_tunnel.py
banyan/controllers/service_web.py
banyan/controllers/shield.py
banyan/controllers/user.py
banyan/core/__init__.py
banyan/core/exc.py
banyan/core/version.py
banyan/ext/__init__.py
banyan/ext/aws/__init__.py
banyan/ext/aws/ec2.py
banyan/ext/azure/__init__.py
banyan/ext/azure/vm.py
banyan/ext/azuread/__init__.py
banyan/ext/azuread/application.py
banyan/ext/iaas/__init__.py
banyan/ext/iaas/aws.py
banyan/ext/iaas/azure_cloud.py
banyan/ext/iaas/base.py
banyan/ext/iaas/gcp.py
banyan/ext/iaas/oracle_cloud.py
banyan/ext/iaas/vmware.py
banyan/ext/idp/__init__.py
banyan/ext/idp/azure_ad.py
banyan/ext/idp/base.py
banyan/ext/idp/okta.py
banyan/ext/okta/__init__.py
banyan/ext/okta/application.py
banyan/ext/vmware/__init__.py
banyan/ext/vmware/vm.py
banyan/lib/__init__.py
banyan/lib/certs.py
banyan/lib/service.py
banyan/lib/cloud/__init__.py
banyan/lib/cloud/aws.py
banyan/model/__init__.py
banyan/model/access_tier.py
pybanyan-0.29.4.dist-info/LICENSE.md
pybanyan-0.29.4.dist-info/METADATA
pybanyan-0.29.4.dist-info/WHEEL
pybanyan-0.29.4.dist-info/entry_points.txt
pybanyan-0.29.4.dist-info/top_level.txt
pybanyan-0.29.4.dist-info/RECORD
