Metadata-Version: 2.1
Name: pybanyan
Version: 0.29.4
Summary: API library and command-line interface for Banyan Security
Home-page: https://github.com/banyansecurity/pybanyan/
Author: Todd Radel
Author-email: todd@banyansecurity.io
License: apache
Requires-Python: ~=3.7
License-File: LICENSE.md
Requires-Dist: dnspython
Requires-Dist: marshmallow
Requires-Dist: marshmallow-dataclass
Requires-Dist: python-dateutil
Requires-Dist: cement (~=3.0)
Requires-Dist: jinja2
Requires-Dist: pyyaml
Requires-Dist: colorlog
Requires-Dist: semver
Requires-Dist: jwt
Requires-Dist: iso8601
Requires-Dist: tabulate
Requires-Dist: pyOpenSSL
Requires-Dist: requests
Requires-Dist: aenum
Requires-Dist: colorama
Requires-Dist: cryptography
Provides-Extra: aws
Requires-Dist: boto3 ; extra == 'aws'
Requires-Dist: ec2-metadata ; extra == 'aws'
Provides-Extra: azure_ad
Requires-Dist: azure-identity ; extra == 'azure_ad'
Requires-Dist: msgraph-core ; extra == 'azure_ad'
Provides-Extra: azure_cloud
Requires-Dist: azure-identity ; extra == 'azure_cloud'
Requires-Dist: azure-mgmt-resource ; extra == 'azure_cloud'
Requires-Dist: azure-mgmt-compute ; extra == 'azure_cloud'
Requires-Dist: azure-mgmt-network ; extra == 'azure_cloud'
Provides-Extra: gcp
Requires-Dist: google-api-python-client ; extra == 'gcp'
Provides-Extra: okta
Requires-Dist: okta ; extra == 'okta'
Provides-Extra: oracle_cloud
Requires-Dist: oci ; extra == 'oracle_cloud'
